.gitignore
README.md
gencodeFile.yml
requirements.txt
setup.cfg
setup.py
jtt_tm_utils/__init__.py
jtt_tm_utils/consul_handle.py
jtt_tm_utils/kong.py
jtt_tm_utils/log.py
jtt_tm_utils/sync_basedata.py
jtt_tm_utils/timeutil.py
jtt_tm_utils.egg-info/PKG-INFO
jtt_tm_utils.egg-info/SOURCES.txt
jtt_tm_utils.egg-info/dependency_links.txt
jtt_tm_utils.egg-info/not-zip-safe
jtt_tm_utils.egg-info/top_level.txt
tests/test_consul.py
tests/test_sync.py
tests/test_syncdata.py
tests/test_task.py